mngdataclean/__init__.py
mngdataclean-0.4.2.dist-info/METADATA
mngdataclean-0.4.2.dist-info/WHEEL
mngdataclean-0.4.2.dist-info/license
mngdataclean-0.4.2.dist-info/top_level.txt
mngdataclean-0.4.2.dist-info/RECORD
