Metadata-Version: 2.1
Name: mngdataclean
Version: 0.4.2
Summary: Text preprocessing package
Home-page: https://github.com/Nagaganesh21/mngdataclean
Author: Nagaganesh
Author-email: mnagaganesh21@gmail.com
License: MIT
Keywords: text,preprocessing
Platform: UNKNOWN
Classifier: Intended Audience :: Developers
Classifier: License :: OSI Approved :: MIT License
Classifier: Programming Language :: Python :: 3.9
License-File: license
Requires-Dist: spacy
Requires-Dist: beautifulsoup4
Requires-Dist: textblob
Requires-Dist: unicodedata2
